deepali/core/__init__.py
deepali/core/_kornia.py
deepali/core/affine.py
deepali/core/argparse.py
deepali/core/bspline.py
deepali/core/collections.py
deepali/core/config.py
deepali/core/cube.py
deepali/core/enum.py
deepali/core/environ.py
deepali/core/flow.py
deepali/core/functional.py
deepali/core/grid.py
deepali/core/image.py
deepali/core/itertools.py
deepali/core/kernels.py
deepali/core/linalg.py
deepali/core/logging.py
deepali/core/math.py
deepali/core/nnutils.py
deepali/core/pathlib.py
deepali/core/pointset.py
deepali/core/psutil.py
deepali/core/random.py
deepali/core/storage.py
deepali/core/tempfile.py
deepali/core/tensor.py
deepali/core/typing.py
deepali/data/__init__.py
deepali/data/collate.py
deepali/data/dataset.py
deepali/data/flow.py
deepali/data/image.py
deepali/data/partition.py
deepali/data/prepare.py
deepali/data/sample.py
deepali/data/sampler.py
deepali/data/tensor.py
deepali/data/transforms/__init__.py
deepali/data/transforms/image.py
deepali/data/transforms/item.py
deepali/losses/__init__.py
deepali/losses/base.py
deepali/losses/bspline.py
deepali/losses/flow.py
deepali/losses/functional.py
deepali/losses/image.py
deepali/losses/params.py
deepali/losses/pointset.py
deepali/modules/__init__.py
deepali/modules/basic.py
deepali/modules/flow.py
deepali/modules/image.py
deepali/modules/lambd.py
deepali/modules/mixins.py
deepali/modules/output.py
deepali/modules/sample.py
deepali/modules/utilities.py
deepali/networks/__init__.py
deepali/networks/resnet.py
deepali/networks/unet.py
deepali/networks/utils.py
deepali/networks/blocks/__init__.py
deepali/networks/blocks/residual.py
deepali/networks/blocks/skip.py
deepali/networks/layers/__init__.py
deepali/networks/layers/acti.py
deepali/networks/layers/conv.py
deepali/networks/layers/join.py
deepali/networks/layers/lambd.py
deepali/networks/layers/linear.py
deepali/networks/layers/norm.py
deepali/networks/layers/pool.py
deepali/networks/layers/upsample.py
deepali/spatial/__init__.py
deepali/spatial/base.py
hf_deepali-0.6.5.dist-info/licenses/LICENSE
hf_deepali-0.6.5.dist-info/METADATA
hf_deepali-0.6.5.dist-info/WHEEL
hf_deepali-0.6.5.dist-info/top_level.txt
hf_deepali-0.6.5.dist-info/RECORD
