Metadata-Version: 2.4
Name: hf-deepali
Version: 0.6.5
Summary: Image, point set, and surface registration library for PyTorch.
Maintainer-email: Andreas Schuh <andreas.schuh@imperial.ac.uk>
License: Apache-2.0
Project-URL: Homepage, https://biomedia.github.io/deepali
Project-URL: Repository, https://github.com/BioMedIA/deepali.git
Project-URL: Bug Tracker, https://github.com/BioMedIA/deepali/issues
Keywords: medical-imaging,image-registration,spatial-transformer-networks
Classifier: Development Status :: 3 - Alpha
Classifier: License :: OSI Approved :: Apache Software License
Classifier: Operating System :: OS Independent
Classifier: Programming Language :: Python :: 3.10
Classifier: Programming Language :: Python :: 3.11
Classifier: Programming Language :: Python :: 3.12
Classifier: Topic :: Software Development :: Libraries
Classifier: Topic :: Scientific/Engineering :: Artificial Intelligence
Classifier: Topic :: Scientific/Engineering :: Image Processing
Classifier: Typing :: Typed
Requires-Python: >=3.9
License-File: LICENSE
Requires-Dist: dacite
Requires-Dist: deprecation
Requires-Dist: packaging
Requires-Dist: pandas
Requires-Dist: ruamel.yaml
Requires-Dist: torch>=1.9
Requires-Dist: typing-extensions
Provides-Extra: all
Requires-Dist: hf-deepali[tests,utils]; extra == "all"
Provides-Extra: utils
Requires-Dist: boto3; extra == "utils"
Requires-Dist: nibabel; extra == "utils"
Requires-Dist: numpy; extra == "utils"
Requires-Dist: scipy; extra == "utils"
Requires-Dist: SimpleITK>=2.0; extra == "utils"
Requires-Dist: vtk>=9.0; extra == "utils"
Provides-Extra: tests
Requires-Dist: pytest; extra == "tests"
Requires-Dist: torchinfo; extra == "tests"
Dynamic: license-file
